{
  "wallet": "0x92672c80d36dcd08172aa1e51dface0f20b70f9a",
  "username": "ckw",
  "total_profit": 886712.54,
  "raw_realized_pnl": 886712.54,
  "total_risked": 35924496.98,
  "overall_roi": 2.47,
  "win_rate": 55.98,
  "avg_bet_size": 18485.9,
  "total_events": 1538,
  "pseudo_sharpe": 0.14,
  "profitable_days": 186,
  "total_days": 360,
  "hedge_count": 412,
  "hedge_risk": 7473265.02,
  "hedge_profit": 764687.17,
  "bond_count": 3,
  "bond_risk": 19914.53,
  "bond_profit": 815.47,
  "open_count": 3,
  "open_risk": 14530.05,
  "open_value": 15729.8,
  "open_pnl": 1962.53,
  "sport_stats": {
    "ESPORTS": {
      "net_profit": 9975.6,
      "roi": 33.82,
      "win_rate": 50.0,
      "events": 2,
      "avg_bet": 14749.18,
      "median_bet": 14749.18
    },
    "MLB": {
      "net_profit": 127897.76,
      "roi": 2.21,
      "win_rate": 58.33,
      "events": 348,
      "avg_bet": 16615.21,
      "median_bet": 11599.96
    },
    "NBA": {
      "net_profit": -550820.32,
      "roi": -6.74,
      "win_rate": 57.08,
      "events": 438,
      "avg_bet": 18656.36,
      "median_bet": 12789.99
    },
    "NFL": {
      "net_profit": 231776.26,
      "roi": 4.26,
      "win_rate": 58.23,
      "events": 237,
      "avg_bet": 22938.43,
      "median_bet": 13132.55
    },
    "NHL": {
      "net_profit": -124556.67,
      "roi": -9.12,
      "win_rate": 47.56,
      "events": 82,
      "avg_bet": 16651.75,
      "median_bet": 10799.69
    },
    "OTHER": {
      "net_profit": 186020.53,
      "roi": 4.69,
      "win_rate": 53.5,
      "events": 243,
      "avg_bet": 16310.79,
      "median_bet": 9699.98
    },
    "POLITICS": {
      "net_profit": -25210.36,
      "roi": -100.0,
      "win_rate": 0.0,
      "events": 2,
      "avg_bet": 12605.18,
      "median_bet": 12605.18
    },
    "SOCCER (EPL)": {
      "net_profit": -15424.08,
      "roi": -4.31,
      "win_rate": 63.16,
      "events": 19,
      "avg_bet": 18856.32,
      "median_bet": 12605.96
    },
    "SOCCER (LaLiga)": {
      "net_profit": 103594.63,
      "roi": 14.43,
      "win_rate": 55.26,
      "events": 38,
      "avg_bet": 18896.05,
      "median_bet": 10000.0
    },
    "SOCCER (Other)": {
      "net_profit": 124260.62,
      "roi": 7.96,
      "win_rate": 54.84,
      "events": 93,
      "avg_bet": 16791.67,
      "median_bet": 11400.0
    },
    "SOCCER (UCL)": {
      "net_profit": 27769.57,
      "roi": 3.1,
      "win_rate": 57.14,
      "events": 14,
      "avg_bet": 64050.95,
      "median_bet": 18549.99
    },
    "TENNIS": {
      "net_profit": 27697.59,
      "roi": 22.92,
      "win_rate": 35.0,
      "events": 20,
      "avg_bet": 6041.29,
      "median_bet": 3000.86
    },
    "WNBA": {
      "net_profit": -21.5,
      "roi": -0.99,
      "win_rate": 50.0,
      "events": 2,
      "avg_bet": 1085.75,
      "median_bet": 1085.75
    }
  },
  "market_stats": {
    "Futures": {
      "net_profit": 18681.37,
      "roi": 6.02,
      "win_rate": 61.54,
      "events": 39,
      "avg_bet": 7952.29,
      "median_bet": 4477.29
    },
    "Moneyline / Match": {
      "net_profit": 1045842.49,
      "roi": 5.12,
      "win_rate": 58.73,
      "events": 1168,
      "avg_bet": 17495.37,
      "median_bet": 10999.69
    },
    "Spread": {
      "net_profit": -685219.61,
      "roi": -14.6,
      "win_rate": 46.5,
      "events": 157,
      "avg_bet": 29886.85,
      "median_bet": 20600.98
    },
    "Totals (O/U)": {
      "net_profit": -256344.6,
      "roi": -8.56,
      "win_rate": 44.83,
      "events": 174,
      "avg_bet": 17208.91,
      "median_bet": 12580.34
    }
  },
  "sport_market_stats": {
    "MLB|Moneyline / Match": {
      "net_profit": 203424.57,
      "roi": 3.62,
      "win_rate": 59.09,
      "events": 330,
      "avg_bet": 17005.84,
      "median_bet": 11840.0
    },
    "MLB|Spread": {
      "net_profit": -89588.7,
      "roi": -96.7,
      "win_rate": 14.29,
      "events": 7,
      "avg_bet": 13234.91,
      "median_bet": 2317.94
    },
    "MLB|Totals (O/U)": {
      "net_profit": 14061.9,
      "roi": 18.14,
      "win_rate": 63.64,
      "events": 11,
      "avg_bet": 7047.43,
      "median_bet": 2511.6
    },
    "NBA|Futures": {
      "net_profit": -3231.8,
      "roi": -7.48,
      "win_rate": 50.0,
      "events": 2,
      "avg_bet": 21591.81,
      "median_bet": 21591.81
    },
    "NBA|Moneyline / Match": {
      "net_profit": 5640.42,
      "roi": 0.11,
      "win_rate": 61.9,
      "events": 336,
      "avg_bet": 14781.18,
      "median_bet": 8738.52
    },
    "NBA|Spread": {
      "net_profit": -378153.98,
      "roi": -15.5,
      "win_rate": 43.66,
      "events": 71,
      "avg_bet": 34363.47,
      "median_bet": 26400.0
    },
    "NBA|Totals (O/U)": {
      "net_profit": -175074.96,
      "roi": -24.25,
      "win_rate": 34.48,
      "events": 29,
      "avg_bet": 24897.24,
      "median_bet": 21400.0
    },
    "NFL|Moneyline / Match": {
      "net_profit": 405767.96,
      "roi": 11.02,
      "win_rate": 61.31,
      "events": 168,
      "avg_bet": 21913.1,
      "median_bet": 13000.0
    },
    "NFL|Spread": {
      "net_profit": -130724.64,
      "roi": -10.43,
      "win_rate": 50.0,
      "events": 42,
      "avg_bet": 29837.86,
      "median_bet": 18787.68
    },
    "NFL|Totals (O/U)": {
      "net_profit": -43267.06,
      "roi": -8.62,
      "win_rate": 51.85,
      "events": 27,
      "avg_bet": 18585.81,
      "median_bet": 11128.4
    },
    "NHL|Futures": {
      "net_profit": -960.0,
      "roi": -100.0,
      "win_rate": 0.0,
      "events": 1,
      "avg_bet": 960.0,
      "median_bet": 960.0
    },
    "NHL|Moneyline / Match": {
      "net_profit": -51956.25,
      "roi": -4.28,
      "win_rate": 51.47,
      "events": 68,
      "avg_bet": 17835.93,
      "median_bet": 12500.0
    },
    "NHL|Spread": {
      "net_profit": -16021.99,
      "roi": -100.0,
      "win_rate": 0.0,
      "events": 1,
      "avg_bet": 16021.99,
      "median_bet": 16021.99
    },
    "NHL|Totals (O/U)": {
      "net_profit": -55618.43,
      "roi": -41.01,
      "win_rate": 33.33,
      "events": 12,
      "avg_bet": 11301.54,
      "median_bet": 8959.24
    },
    "Other|Futures": {
      "net_profit": 54244.23,
      "roi": 23.23,
      "win_rate": 70.0,
      "events": 30,
      "avg_bet": 7784.15,
      "median_bet": 4531.82
    },
    "Other|Moneyline / Match": {
      "net_profit": 242392.59,
      "roi": 13.22,
      "win_rate": 54.78,
      "events": 115,
      "avg_bet": 15939.71,
      "median_bet": 9549.94
    },
    "Other|Spread": {
      "net_profit": -141788.65,
      "roi": -20.49,
      "win_rate": 48.15,
      "events": 27,
      "avg_bet": 25630.1,
      "median_bet": 17596.3
    },
    "Other|Totals (O/U)": {
      "net_profit": 31172.36,
      "roi": 2.59,
      "win_rate": 46.48,
      "events": 71,
      "avg_bet": 16970.67,
      "median_bet": 14400.0
    },
    "Politics|Futures": {
      "net_profit": -25210.36,
      "roi": -100.0,
      "win_rate": 0.0,
      "events": 2,
      "avg_bet": 12605.18,
      "median_bet": 12605.18
    },
    "Soccer|Futures": {
      "net_profit": 55.96,
      "roi": 6.81,
      "win_rate": 100.0,
      "events": 1,
      "avg_bet": 821.16,
      "median_bet": 821.16
    },
    "Soccer|Moneyline / Match": {
      "net_profit": 153435.27,
      "roi": 7.3,
      "win_rate": 56.41,
      "events": 117,
      "avg_bet": 17962.46,
      "median_bet": 11399.99
    },
    "Soccer|Spread": {
      "net_profit": 71058.36,
      "roi": 35.79,
      "win_rate": 77.78,
      "events": 9,
      "avg_bet": 22062.19,
      "median_bet": 11357.56
    },
    "Soccer|Totals (O/U)": {
      "net_profit": -12118.42,
      "roi": -3.6,
      "win_rate": 43.48,
      "events": 23,
      "avg_bet": 14650.25,
      "median_bet": 10600.0
    },
    "Tennis|Futures": {
      "net_profit": -1192.17,
      "roi": -84.25,
      "win_rate": 50.0,
      "events": 2,
      "avg_bet": 707.52,
      "median_bet": 707.52
    },
    "Tennis|Moneyline / Match": {
      "net_profit": 28889.76,
      "roi": 24.19,
      "win_rate": 33.33,
      "events": 18,
      "avg_bet": 6633.93,
      "median_bet": 3094.1
    },
    "UCL|Moneyline / Match": {
      "net_profit": 43269.57,
      "roi": 4.91,
      "win_rate": 61.54,
      "events": 13,
      "avg_bet": 67785.63,
      "median_bet": 20699.97
    },
    "UCL|Totals (O/U)": {
      "net_profit": -15500.0,
      "roi": -100.0,
      "win_rate": 0.0,
      "events": 1,
      "avg_bet": 15500.0,
      "median_bet": 15500.0
    },
    "WNBA|Moneyline / Match": {
      "net_profit": -21.5,
      "roi": -0.99,
      "win_rate": 50.0,
      "events": 2,
      "avg_bet": 1085.75,
      "median_bet": 1085.75
    },
    "eSports|Futures": {
      "net_profit": -5024.5,
      "roi": -100.0,
      "win_rate": 0.0,
      "events": 1,
      "avg_bet": 5024.5,
      "median_bet": 5024.5
    },
    "eSports|Moneyline / Match": {
      "net_profit": 15000.1,
      "roi": 61.29,
      "win_rate": 100.0,
      "events": 1,
      "avg_bet": 24473.85,
      "median_bet": 24473.85
    }
  },
  "price_stats": {
    "Favorite (60-80c)": {
      "net_profit": 363267.92,
      "roi": 3.6,
      "win_rate": 70.75,
      "events": 441
    },
    "Flip (40-60c)": {
      "net_profit": -262576.46,
      "roi": -1.81,
      "win_rate": 51.24,
      "events": 806
    },
    "Longshot (0-20c)": {
      "net_profit": -77344.26,
      "roi": -39.96,
      "win_rate": 18.42,
      "events": 38
    },
    "Safe (80-100c)": {
      "net_profit": 106012.53,
      "roi": 5.98,
      "win_rate": 90.14,
      "events": 71
    },
    "Underdog (20-40c)": {
      "net_profit": -6400.09,
      "roi": -0.35,
      "win_rate": 35.71,
      "events": 182
    }
  },
  "side_stats": {
    "No": {
      "net_profit": -78348.13,
      "roi": -4.92,
      "positions": 76
    },
    "Specific Selection": {
      "net_profit": 107063.56,
      "roi": 0.41,
      "positions": 1722
    },
    "Yes": {
      "net_profit": 94244.22,
      "roi": 11.91,
      "positions": 88
    }
  },
  "monthly_pnl": {
    "1970-01": 845.05,
    "2024-07": 4309.96,
    "2024-11": -30438.17,
    "2024-12": -39785.15,
    "2025-01": 50062.39,
    "2025-02": -19017.89,
    "2025-03": 12098.22,
    "2025-04": 31170.85,
    "2025-05": -15623.41,
    "2025-06": 25205.24,
    "2025-07": -98857.2,
    "2025-08": -157106.53,
    "2025-09": 425989.77,
    "2025-10": 320489.72,
    "2025-11": -150616.88,
    "2025-12": 284143.54,
    "2026-01": -407797.17,
    "2026-02": -47470.45,
    "2026-03": -66604.77,
    "2026-04": 991.44
  },
  "top_wins": [
    {
      "title": "UFC 323: Pantoja vs. Van (Flyweight, Main Card)",
      "sport_type": "OTHER",
      "total_pnl": 181904.396589,
      "total_cost": 88095.19758880368,
      "avg_price": 0.326279,
      "status": "closed"
    },
    {
      "title": "Will Paris Saint-Germain FC win on 2026-01-20?",
      "sport_type": "SOCCER (UCL)",
      "total_pnl": 175000.2,
      "total_cost": 124999.79999999999,
      "avg_price": 0.416666,
      "status": "closed"
    },
    {
      "title": "Will AS Monaco FC win on 2026-01-16?",
      "sport_type": "SOCCER (Other)",
      "total_pnl": 132400.56,
      "total_cost": 107599.44,
      "avg_price": 0.448331,
      "status": "closed"
    },
    {
      "title": "Will Villarreal CF win on 2026-01-20?",
      "sport_type": "SOCCER (UCL)",
      "total_pnl": 124000.0,
      "total_cost": 76000.0,
      "avg_price": 0.38,
      "status": "closed"
    },
    {
      "title": "East Texas A&M Lions vs. Incarnate Word Cardinals: O/U 141.5",
      "sport_type": "OTHER",
      "total_pnl": 114500.197114,
      "total_cost": 85499.79788207,
      "avg_price": 0.4276208522439057,
      "status": "closed"
    }
  ],
  "top_losses": [
    {
      "title": "Will Juventus FC win on 2026-01-21?",
      "sport_type": "SOCCER (UCL)",
      "total_pnl": -175000.0,
      "total_cost": 175000.0,
      "avg_price": 0.4375,
      "status": "closed"
    },
    {
      "title": "Spread: Rockets (-8.5)",
      "sport_type": "NBA",
      "total_pnl": -146999.986353,
      "total_cost": 146999.98635398998,
      "avg_price": 0.49000000000000005,
      "status": "closed"
    },
    {
      "title": "Will Olympiak\u00f3s SFP win on 2026-01-20?",
      "sport_type": "SOCCER (UCL)",
      "total_pnl": -111500.0,
      "total_cost": 111500.0,
      "avg_price": 0.5575,
      "status": "closed"
    },
    {
      "title": "Spread: Hornets (-2.5)",
      "sport_type": "NBA",
      "total_pnl": -95798.05951299999,
      "total_cost": 95798.0595135372,
      "avg_price": 0.4571842776180273,
      "status": "closed"
    },
    {
      "title": "Tigers vs. Guardians",
      "sport_type": "MLB",
      "total_pnl": -94342.708,
      "total_cost": 110199.99999999999,
      "avg_price": 0.58,
      "status": "closed"
    }
  ],
  "top_sport": "NFL",
  "best_price_bucket": "Safe (80-100c)",
  "best_market": "Moneyline / Match",
  "quality_score": 7,
  "tier": "C-Tier",
  "tags": [
    "\u2b50 C-Tier",
    "\u2696\ufe0f Hedge / MM-heavy \u2014 quality blends dashboard + directional ROI",
    "\u26bd Global Soccer",
    "\ud83c\udfc8 NFL Specialist",
    "\ud83c\udfbe Tennis Expert",
    "\u2705 Yes-Side Specialist",
    "\ud83d\udc0b Mega Whale",
    "\u26d4 Fade NBA",
    "\u26d4 Fade Spreads"
  ],
  "tail_guide": "How to Tail ckw [C-Tier]\n\n\ud83d\udfe2 AUTO-TAIL:\n   SOCCER (Other) \u2014 8.0% ROI, 93 events, +$124,261\n   SOCCER (LaLiga) \u2014 14.4% ROI, 38 events, +$103,595\n   TENNIS \u2014 22.9% ROI, 20 events, +$27,698\n\n\ud83d\udd34 DO NOT TAIL:\n   NBA \u2014 ROI -6.7%, $-550,820\n   NHL \u2014 ROI -9.1%, $-124,557\n   SOCCER (EPL) \u2014 ROI -4.3%, $-15,424\n\n\ud83d\udcc8 Stick to Moneylines (5.1% ROI over 1168 events)\n\u26d4 Mute all Spread bets (-14.6% ROI)\n\u26d4 Mute all O/U bets (-8.6% ROI)\n\ud83c\udfaf Best price zone: Safe (80-100c) (6.0% ROI, 71 events)\n\u26a0\ufe0f  Strip any bet at avgPrice \u2265 0.95 \u2014 those are bond-yield trades, not signals\n\ud83d\udca1 87% of edge from 'Specific' side \u2014 copy that side only\n\u26a1 Normal bet ~$18,486 \u2014 alert at 3x average for high-conviction plays",
  "do_not_tail_sports": [
    "NBA",
    "NHL",
    "SOCCER (EPL)"
  ],
  "auto_tail_sports": [
    "SOCCER (LaLiga)",
    "SOCCER (Other)",
    "TENNIS"
  ],
  "do_not_tail_market_types": [
    "Spread",
    "Totals (O/U)"
  ],
  "do_not_tail_sides": [],
  "score_breakdown": {
    "sharpe_score": 0.5,
    "roi_score": 3.5,
    "wr_score": 8.0,
    "cons_score": 5.2,
    "vol_score": 5,
    "base_score": 22.2,
    "flip_bonus": 0,
    "leakage_penalty": 15,
    "midzone_roi": -1.1,
    "directional_roi": 0.43,
    "roi_dashboard": 2.47,
    "roi_for_quality": 2.1,
    "hedge_risk_frac": 0.208,
    "hedge_profit_share": 0.862
  }
}