[
  {
    "username": "RN1",
    "wallet": "0x2005d16a84ceefa912d4e380cd32e7ff827875ea",
    "changes": [
      "tier: S-Tier -> B-Tier",
      "quality_score: 100 -> 47",
      "ROI: 97.7% -> 4.2%",
      "total_profit: $12,067,099 -> $6,515,005",
      "tail_guide (do-not-tail / tail logic) updated"
    ],
    "previous": {
      "tier": "S-Tier",
      "quality_score": 100,
      "overall_roi": 97.71,
      "total_profit": 12067098.98
    },
    "new": {
      "tier": "B-Tier",
      "quality_score": 47,
      "overall_roi": 4.24,
      "total_profit": 6515004.6
    }
  }
]