{
  "wallet": "0xc65ca4755436f82d8eb461e65781584b8cadea39",
  "username": "UAEVALORANTFAN",
  "total_profit": 25688.97,
  "raw_realized_pnl": 25688.97,
  "total_risked": 9489291.73,
  "overall_roi": 0.27,
  "win_rate": 53.32,
  "avg_bet_size": 12278.69,
  "total_events": 754,
  "pseudo_sharpe": 0.1,
  "profitable_days": 56,
  "total_days": 102,
  "hedge_count": 58,
  "hedge_risk": 231161.52,
  "hedge_profit": -1575.0,
  "bond_count": 0,
  "bond_risk": 0.0,
  "bond_profit": 0.0,
  "open_count": 2,
  "open_risk": 68215.33,
  "open_value": 105186.01,
  "open_pnl": 36970.69,
  "sport_stats": {
    "ESPORTS": {
      "net_profit": 72528.34,
      "roi": 2.41,
      "win_rate": 52.94,
      "events": 323,
      "avg_bet": 9330.88,
      "median_bet": 3383.5
    },
    "NBA": {
      "net_profit": 53651.7,
      "roi": 2.63,
      "win_rate": 51.54,
      "events": 130,
      "avg_bet": 15674.02,
      "median_bet": 10510.37
    },
    "NFL": {
      "net_profit": 27768.52,
      "roi": 15.52,
      "win_rate": 54.55,
      "events": 11,
      "avg_bet": 16264.06,
      "median_bet": 17298.8
    },
    "NHL": {
      "net_profit": -45040.12,
      "roi": -3.02,
      "win_rate": 60.32,
      "events": 63,
      "avg_bet": 23681.54,
      "median_bet": 19500.25
    },
    "OTHER": {
      "net_profit": -226538.89,
      "roi": -16.01,
      "win_rate": 50.46,
      "events": 109,
      "avg_bet": 12979.8,
      "median_bet": 4175.5
    },
    "SOCCER (EPL)": {
      "net_profit": 12506.55,
      "roi": 7.61,
      "win_rate": 50.0,
      "events": 12,
      "avg_bet": 13687.19,
      "median_bet": 10656.98
    },
    "SOCCER (LaLiga)": {
      "net_profit": -34005.6,
      "roi": -14.03,
      "win_rate": 52.17,
      "events": 23,
      "avg_bet": 10540.19,
      "median_bet": 5399.97
    },
    "SOCCER (Other)": {
      "net_profit": 124374.53,
      "roi": 20.86,
      "win_rate": 59.57,
      "events": 47,
      "avg_bet": 12684.86,
      "median_bet": 8650.0
    },
    "SOCCER (UCL)": {
      "net_profit": 65105.12,
      "roi": 87.62,
      "win_rate": 83.33,
      "events": 6,
      "avg_bet": 12384.09,
      "median_bet": 7597.19
    },
    "TENNIS": {
      "net_profit": 13884.51,
      "roi": 31.68,
      "win_rate": 46.67,
      "events": 30,
      "avg_bet": 1461.04,
      "median_bet": 253.95
    }
  },
  "market_stats": {
    "Futures": {
      "net_profit": -13476.83,
      "roi": -7.34,
      "win_rate": 66.67,
      "events": 27,
      "avg_bet": 6797.94,
      "median_bet": 5060.37
    },
    "Moneyline / Match": {
      "net_profit": 279191.59,
      "roi": 4.21,
      "win_rate": 53.79,
      "events": 541,
      "avg_bet": 12259.69,
      "median_bet": 4873.23
    },
    "Spread": {
      "net_profit": 125606.58,
      "roi": 10.42,
      "win_rate": 50.0,
      "events": 96,
      "avg_bet": 12551.12,
      "median_bet": 6056.23
    },
    "Totals (O/U)": {
      "net_profit": -327086.68,
      "roi": -26.44,
      "win_rate": 50.0,
      "events": 90,
      "avg_bet": 13746.49,
      "median_bet": 9653.91
    }
  },
  "sport_market_stats": {
    "NBA|Moneyline / Match": {
      "net_profit": 70383.31,
      "roi": 7.27,
      "win_rate": 53.57,
      "events": 56,
      "avg_bet": 17297.47,
      "median_bet": 12055.93
    },
    "NBA|Spread": {
      "net_profit": 85469.6,
      "roi": 11.68,
      "win_rate": 51.22,
      "events": 41,
      "avg_bet": 17846.53,
      "median_bet": 13000.0
    },
    "NBA|Totals (O/U)": {
      "net_profit": -102201.21,
      "roi": -30.3,
      "win_rate": 48.48,
      "events": 33,
      "avg_bet": 10219.88,
      "median_bet": 5292.51
    },
    "NFL|Moneyline / Match": {
      "net_profit": 38610.02,
      "roi": 113.93,
      "win_rate": 100.0,
      "events": 1,
      "avg_bet": 33889.98,
      "median_bet": 33889.98
    },
    "NFL|Spread": {
      "net_profit": 8145.21,
      "roi": 6.57,
      "win_rate": 50.0,
      "events": 8,
      "avg_bet": 15489.62,
      "median_bet": 16747.57
    },
    "NFL|Totals (O/U)": {
      "net_profit": -18986.71,
      "roi": -89.99,
      "win_rate": 50.0,
      "events": 2,
      "avg_bet": 10548.87,
      "median_bet": 10548.87
    },
    "NHL|Futures": {
      "net_profit": 4499.9,
      "roi": 81.82,
      "win_rate": 100.0,
      "events": 1,
      "avg_bet": 5499.88,
      "median_bet": 5499.88
    },
    "NHL|Moneyline / Match": {
      "net_profit": -74081.83,
      "roi": -5.06,
      "win_rate": 57.63,
      "events": 59,
      "avg_bet": 24819.87,
      "median_bet": 21199.99
    },
    "NHL|Totals (O/U)": {
      "net_profit": 24541.81,
      "roi": 111.23,
      "win_rate": 100.0,
      "events": 3,
      "avg_bet": 7354.93,
      "median_bet": 9199.98
    },
    "Other|Futures": {
      "net_profit": 6699.98,
      "roi": 203.03,
      "win_rate": 100.0,
      "events": 1,
      "avg_bet": 3299.99,
      "median_bet": 3299.99
    },
    "Other|Moneyline / Match": {
      "net_profit": -87578.99,
      "roi": -14.93,
      "win_rate": 47.76,
      "events": 67,
      "avg_bet": 8753.71,
      "median_bet": 1695.6
    },
    "Other|Spread": {
      "net_profit": 109559.34,
      "roi": 60.67,
      "win_rate": 76.47,
      "events": 17,
      "avg_bet": 10622.59,
      "median_bet": 4175.5
    },
    "Other|Totals (O/U)": {
      "net_profit": -255219.24,
      "roi": -39.6,
      "win_rate": 37.5,
      "events": 24,
      "avg_bet": 26850.65,
      "median_bet": 28719.61
    },
    "Soccer|Moneyline / Match": {
      "net_profit": 145320.7,
      "roi": 20.12,
      "win_rate": 59.62,
      "events": 52,
      "avg_bet": 13891.8,
      "median_bet": 11256.94
    },
    "Soccer|Spread": {
      "net_profit": -68254.96,
      "roi": -87.22,
      "win_rate": 16.67,
      "events": 6,
      "avg_bet": 13042.49,
      "median_bet": 9834.88
    },
    "Soccer|Totals (O/U)": {
      "net_profit": 25809.74,
      "roi": 12.76,
      "win_rate": 58.33,
      "events": 24,
      "avg_bet": 8426.27,
      "median_bet": 5727.32
    },
    "Tennis|Moneyline / Match": {
      "net_profit": 14134.48,
      "roi": 32.45,
      "win_rate": 46.15,
      "events": 26,
      "avg_bet": 1675.37,
      "median_bet": 255.6
    },
    "Tennis|Spread": {
      "net_profit": 1.7,
      "roi": 15.36,
      "win_rate": 50.0,
      "events": 2,
      "avg_bet": 5.53,
      "median_bet": 5.53
    },
    "Tennis|Totals (O/U)": {
      "net_profit": -251.67,
      "roi": -96.55,
      "win_rate": 50.0,
      "events": 2,
      "avg_bet": 130.33,
      "median_bet": 130.33
    },
    "UCL|Moneyline / Match": {
      "net_profit": 65105.12,
      "roi": 87.62,
      "win_rate": 83.33,
      "events": 6,
      "avg_bet": 12384.09,
      "median_bet": 7597.19
    },
    "eSports|Futures": {
      "net_profit": -24676.71,
      "roi": -14.12,
      "win_rate": 64.0,
      "events": 25,
      "avg_bet": 6989.78,
      "median_bet": 5060.37
    },
    "eSports|Moneyline / Match": {
      "net_profit": 107298.77,
      "roi": 3.92,
      "win_rate": 53.28,
      "events": 274,
      "avg_bet": 9995.75,
      "median_bet": 3419.38
    },
    "eSports|Spread": {
      "net_profit": -9314.31,
      "roi": -10.3,
      "win_rate": 36.36,
      "events": 22,
      "avg_bet": 4110.6,
      "median_bet": 1936.9
    },
    "eSports|Totals (O/U)": {
      "net_profit": -779.41,
      "roi": -7.91,
      "win_rate": 50.0,
      "events": 2,
      "avg_bet": 4929.37,
      "median_bet": 4929.37
    }
  },
  "price_stats": {
    "Favorite (60-80c)": {
      "net_profit": -210676.18,
      "roi": -7.34,
      "win_rate": 62.79,
      "events": 172
    },
    "Flip (40-60c)": {
      "net_profit": 252243.02,
      "roi": 4.43,
      "win_rate": 53.81,
      "events": 433
    },
    "Longshot (0-20c)": {
      "net_profit": -12641.6,
      "roi": -100.0,
      "win_rate": 0.0,
      "events": 6
    },
    "Safe (80-100c)": {
      "net_profit": 11785.61,
      "roi": 15.52,
      "win_rate": 87.5,
      "events": 8
    },
    "Underdog (20-40c)": {
      "net_profit": 23523.8,
      "roi": 3.9,
      "win_rate": 40.0,
      "events": 135
    }
  },
  "side_stats": {
    "No": {
      "net_profit": -44129.99,
      "roi": -21.12,
      "positions": 23
    },
    "Specific Selection": {
      "net_profit": -141552.83,
      "roi": -1.64,
      "positions": 813
    },
    "Yes": {
      "net_profit": 249917.48,
      "roi": 59.03,
      "positions": 49
    }
  },
  "monthly_pnl": {
    "2025-12": 191301.65,
    "2026-01": -256122.4,
    "2026-02": -133966.3,
    "2026-03": 230251.44,
    "2026-04": -4200.43
  },
  "top_wins": [
    {
      "title": "Counter-Strike: Aurora Gaming vs TheMongolz (BO3) - BLAST Open Rotterdam Playoffs",
      "sport_type": "ESPORTS",
      "total_pnl": 77354.11743,
      "total_cost": 75218.29442019027,
      "avg_price": 0.49423032065738676,
      "status": "closed"
    },
    {
      "title": "Valorant: Team Liquid vs Gentle Mates (BO3) - VCT Masters Santiago Group Stage",
      "sport_type": "ESPORTS",
      "total_pnl": 59782.79333499999,
      "total_cost": 67091.96285720317,
      "avg_price": 0.5307404288852228,
      "status": "closed"
    },
    {
      "title": "Spread: Cavaliers (-12.5)",
      "sport_type": "NBA",
      "total_pnl": 57642.475431000006,
      "total_cost": 62442.06106121611,
      "avg_price": 0.5199841989339076,
      "status": "closed"
    },
    {
      "title": "Spread: Thunder (-18.5)",
      "sport_type": "NBA",
      "total_pnl": 48956.124826,
      "total_cost": 80594.81625247236,
      "avg_price": 0.5027512108654467,
      "status": "closed"
    },
    {
      "title": "Spread: 76ers (-9.5)",
      "sport_type": "NBA",
      "total_pnl": 48307.16,
      "total_cost": 48307.16,
      "avg_price": 0.5,
      "status": "closed"
    }
  ],
  "top_losses": [
    {
      "title": "Counter-Strike: Team Falcons vs PARIVISION (BO3) - BLAST Open Rotterdam Playoffs",
      "sport_type": "ESPORTS",
      "total_pnl": -101736.397349,
      "total_cost": 101736.39734953998,
      "avg_price": 0.6199999999999999,
      "status": "closed"
    },
    {
      "title": "Valorant: Pcific Esports vs ULF Esports - Map 2 Winner",
      "sport_type": "ESPORTS",
      "total_pnl": -83131.802946,
      "total_cost": 83131.80294679983,
      "avg_price": 0.655191790521357,
      "status": "closed"
    },
    {
      "title": "Islanders vs. Oilers",
      "sport_type": "NHL",
      "total_pnl": -81435.0,
      "total_cost": 81435.0,
      "avg_price": 0.61,
      "status": "closed"
    },
    {
      "title": "Wild vs. Bruins",
      "sport_type": "NHL",
      "total_pnl": -70719.96229,
      "total_cost": 70719.96229064,
      "avg_price": 0.52,
      "status": "closed"
    },
    {
      "title": "Rockets vs. Trail Blazers",
      "sport_type": "NBA",
      "total_pnl": -62432.628888,
      "total_cost": 62432.6288887,
      "avg_price": 0.7,
      "status": "closed"
    }
  ],
  "top_sport": "SOCCER (Other)",
  "best_price_bucket": "Flip (40-60c)",
  "best_market": "Moneyline / Match",
  "quality_score": 2,
  "tier": "C-Tier",
  "tags": [
    "\u2b50 C-Tier",
    "\u26bd Global Soccer",
    "\ud83c\udfbe Tennis Expert",
    "\u2705 Yes-Side Specialist",
    "\ud83d\udc0b Mega Whale",
    "\u26d4 Fade LaLiga"
  ],
  "tail_guide": "How to Tail UAEVALORANTFAN [C-Tier]\n\n\ud83d\udfe2 AUTO-TAIL:\n   SOCCER (Other) \u2014 20.9% ROI, 47 events, +$124,375\n   TENNIS \u2014 31.7% ROI, 30 events, +$13,885\n\n\ud83d\udd34 DO NOT TAIL:\n   OTHER \u2014 ROI -16.0%, $-226,539\n   NHL \u2014 ROI -3.0%, $-45,040\n   SOCCER (LaLiga) \u2014 ROI -14.0%, $-34,006\n\n\ud83d\udcc8 Stick to Moneylines (4.2% ROI over 541 events)\n\u26d4 Mute all O/U bets (-26.4% ROI)\n\ud83c\udfaf Best price zone: Flip (40-60c) (4.4% ROI, 433 events)\n\u26a0\ufe0f  Strip any bet at avgPrice \u2265 0.95 \u2014 those are bond-yield trades, not signals\n\ud83d\udca1 389% of edge from 'Yes' side \u2014 copy that side only\n\u26a1 Normal bet ~$12,279 \u2014 alert at 3x average for high-conviction plays",
  "do_not_tail_sports": [
    "NHL",
    "OTHER",
    "SOCCER (LaLiga)"
  ],
  "auto_tail_sports": [
    "SOCCER (Other)",
    "TENNIS"
  ],
  "do_not_tail_market_types": [
    "Totals (O/U)"
  ],
  "do_not_tail_sides": [],
  "score_breakdown": {
    "sharpe_score": 0.4,
    "roi_score": 1.2,
    "wr_score": 5.3,
    "cons_score": 5.5,
    "vol_score": 5,
    "base_score": 17.4,
    "flip_bonus": 0,
    "leakage_penalty": 15,
    "midzone_roi": 4.2,
    "directional_roi": 0.69,
    "roi_dashboard": 0.27,
    "roi_for_quality": 0.69,
    "hedge_risk_frac": 0.024,
    "hedge_profit_share": -0.061
  }
}